snails.py
snails-2.0.dist-info/LICENSE
snails-2.0.dist-info/METADATA
snails-2.0.dist-info/WHEEL
snails-2.0.dist-info/top_level.txt
snails-2.0.dist-info/RECORD
