Metadata-Version: 2.1
Name: snails
Version: 2.0
Summary: minimal smtpd handler
Home-page: https://github.com/numberoverzero/snails
Author: Joe Cross
Author-email: joe.mcross@gmail.com
License: MIT
Platform: any
Requires-Dist: aiosmtpd
